{
  "type": "rankgroups",
  "groups": {
    "testgroup": {
      "prefix": "test",
      "permissions" : ["eins", "zwei"],
      "priority": 1,
      "color": "ยง2",
      "ranks": ["srTest", "test"],
      "discordRoleID": "556455456456"
    }
  }
}

{
  "type": "ranks",
  "ranks": {
    "srTest": {
      "extraPermissions": ["sd", "Sasdasd"],
      "parent": "testgroup",
      "discordRoleID": "556455456456",
      "privateDiscordRoleID": "556455456456"
    },
    "test": {
      "extraPermissions": ["sd", "Sasdasd"],
      "parent": "testgroup",
      "discordRoleID": "556455456456",
      "privateDiscordRoleID": "556455456456"
    }
  }
}